design.sv
// Code your design here
module queue(
  input [1:0] New,
  input [1:0] Done,
  input [1:0] Reset,
  output [7:0] Current_Client,
  output [7:0] Total_Clients,
  output [1:0] Full);
  
  reg [7:0] Total_Clients_R;
  reg [7:0] Current_Client_R;
  assign Full=Total_Clients_R==7'b1100100;
  assign Current_Client=Current_Client_R;
  assign Total_Clients=Total_Clients_R;
  
  always@(posedge New) begin
    if(Total_Clients_R<7'b1100100)
      Total_Clients_R<=Total_Clients_R+7'b0000001;
  end
  
  always@(posedge Done)begin
    if(Current_Client_R<Total_Clients_R)
      Current_Client_R<=Current_Client_R+7'b0000001;
  end
  
  always@(posedge Reset)begin
    Current_Client_R<=7'b0000000;
    Total_Clients_R<=7'b0000000;
  end
  
  
endmodule

testbench.sv
// Code your testbench here
// or browse Examples
module testbench;
  integer i;
  reg [1:0] New_R;
  reg [1:0] Done_R;
  reg [1:0] Reset_R;
  reg [7:0] Current_Client_R;
  reg [7:0] Total_Clients_R;
  
  wire [1:0] New_W;
  wire [1:0] Done_W;
  wire [1:0] Reset_W;
  wire [7:0] Current_Client_W;
  wire [7:0] Total_Clients_W;
  wire [1:0] Full_W;
  
  
  
  queue Q(New_W,Done_W,Reset_W,Current_Client_W,Total_Clients_W,Full_W);
  
  assign New_W=New_R;
  assign Done_W=Done_R;
  assign Reset_W=Reset_R;
  
  initial begin
    $dumpfile("dump.vcd");
    $dumpvars(0,testbench);
    Reset_R<=1'b1;
      $display("New=%b Total_Clients=%b Current_Client=%b",New_W,Total_Clients_W,Current_Client_W);
    #0.5 Reset_R<=1'b0;
    for(i=0; i<102; i++)begin
      New_R=1'b1;
     $display("New=%b Total_Clients=%b Current_Client=%b",New_W,Total_Clients_W,Current_Client_W);
      #0.5Done_R=1'b0;
      #0.5Reset_R=1'b0;
      #0.5New_R=1'b0;
      #0.6$display("New=%b Total_Clients=%b Current_Client=%b",New_W,Total_Clients_W,Current_Client_W);
    end
	$display("Full Clients,Lets serve them");
    for(i=0; i<102; i++)begin
      Done_R=1'b1;
     $display("Done=%b Total_Clients=%b Current_Client=%b",Done_W,Total_Clients_W,Current_Client_W);
      #0.5Done_R=1'b0;
      #0.5Reset_R=1'b0;
      #0.5New_R=1'b0;
     #0.6$display("Done=%b Total_Clients=%b Current_Client=%b",Done_W,Total_Clients_W,Current_Client_W);
    end
	$display("All are served");
    Reset_R=1'b1;
    #0.5$display("New=%b Total_Clients=%b Current_Client=%b",New_W,Total_Clients_W,Current_Client_W);
    $finish;
  end

  
  
endmodule

dump.vcd
$date
	Tue Jun 20 10:34:45 2023
$end
$version
	Icarus Verilog
$end
$timescale
	1s
$end
$scope module testbench $end
$var wire 2 ! Done_W [1:0] $end
$var wire 2 " New_W [1:0] $end
$var wire 2 # Reset_W [1:0] $end
$var wire 8 $ Total_Clients_W [7:0] $end
$var wire 2 % Full_W [1:0] $end
$var wire 8 & Current_Client_W [7:0] $end
$var reg 2 ' Done_R [1:0] $end
$var reg 2 ( New_R [1:0] $end
$var reg 2 ) Reset_R [1:0] $end
$var integer 32 * i [31:0] $end
$scope module Q $end
$var wire 8 + Current_Client [7:0] $end
$var wire 2 , Done [1:0] $end
$var wire 2 - New [1:0] $end
$var wire 2 . Reset [1:0] $end
$var wire 8 / Total_Clients [7:0] $end
$var wire 2 0 Full [1:0] $end
$var reg 8 1 Current_Client_R [7:0] $end
$var reg 8 2 Total_Clients_R [7:0] $end
$upscope $end
$upscope $end
$enddefinitions $end
$comment Show the parameter values. $end
$dumpall
$end
#0
$dumpvars
b0 2
b0 1
b0 0
b0 /
b1 .
bx -
bx ,
b0 +
bx *
b1 )
bx (
bx '
b0 &
b0 %
b0 $
b1 #
bx "
bx !
$end
#1
b1 $
b1 /
b1 2
b0 #
b0 .
b0 )
b1 "
b1 -
b1 (
b0 *
#2
b0 !
b0 ,
b0 '
#4
b0 "
b0 -
b0 (
#5
b10 $
b10 /
b10 2
b1 "
b1 -
b1 (
b1 *
#8
b0 "
b0 -
b0 (
#9
b11 $
b11 /
b11 2
b1 "
b1 -
b1 (
b10 *
#12
b0 "
b0 -
b0 (
#13
b100 $
b100 /
b100 2
b1 "
b1 -
b1 (
b11 *
#16
b0 "
b0 -
b0 (
#17
b101 $
b101 /
b101 2
b1 "
b1 -
b1 (
b100 *
#20
b0 "
b0 -
b0 (
#21
b110 $
b110 /
b110 2
b1 "
b1 -
b1 (
b101 *
#24
b0 "
b0 -
b0 (
#25
b111 $
b111 /
b111 2
b1 "
b1 -
b1 (
b110 *
#28
b0 "
b0 -
b0 (
#29
b1000 $
b1000 /
b1000 2
b1 "
b1 -
b1 (
b111 *
#32
b0 "
b0 -
b0 (
#33
b1001 $
b1001 /
b1001 2
b1 "
b1 -
b1 (
b1000 *
#36
b0 "
b0 -
b0 (
#37
b1010 $
b1010 /
b1010 2
b1 "
b1 -
b1 (
b1001 *
#40
b0 "
b0 -
b0 (
#41
b1011 $
b1011 /
b1011 2
b1 "
b1 -
b1 (
b1010 *
#44
b0 "
b0 -
b0 (
#45
b1100 $
b1100 /
b1100 2
b1 "
b1 -
b1 (
b1011 *
#48
b0 "
b0 -
b0 (
#49
b1101 $
b1101 /
b1101 2
b1 "
b1 -
b1 (
b1100 *
#52
b0 "
b0 -
b0 (
#53
b1110 $
b1110 /
b1110 2
b1 "
b1 -
b1 (
b1101 *
#56
b0 "
b0 -
b0 (
#57
b1111 $
b1111 /
b1111 2
b1 "
b1 -
b1 (
b1110 *
#60
b0 "
b0 -
b0 (
#61
b10000 $
b10000 /
b10000 2
b1 "
b1 -
b1 (
b1111 *
#64
b0 "
b0 -
b0 (
#65
b10001 $
b10001 /
b10001 2
b1 "
b1 -
b1 (
b10000 *
#68
b0 "
b0 -
b0 (
#69
b10010 $
b10010 /
b10010 2
b1 "
b1 -
b1 (
b10001 *
#72
b0 "
b0 -
b0 (
#73
b10011 $
b10011 /
b10011 2
b1 "
b1 -
b1 (
b10010 *
#76
b0 "
b0 -
b0 (
#77
b10100 $
b10100 /
b10100 2
b1 "
b1 -
b1 (
b10011 *
#80
b0 "
b0 -
b0 (
#81
b10101 $
b10101 /
b10101 2
b1 "
b1 -
b1 (
b10100 *
#84
b0 "
b0 -
b0 (
#85
b10110 $
b10110 /
b10110 2
b1 "
b1 -
b1 (
b10101 *
#88
b0 "
b0 -
b0 (
#89
b10111 $
b10111 /
b10111 2
b1 "
b1 -
b1 (
b10110 *
#92
b0 "
b0 -
b0 (
#93
b11000 $
b11000 /
b11000 2
b1 "
b1 -
b1 (
b10111 *
#96
b0 "
b0 -
b0 (
#97
b11001 $
b11001 /
b11001 2
b1 "
b1 -
b1 (
b11000 *
#100
b0 "
b0 -
b0 (
#101
b11010 $
b11010 /
b11010 2
b1 "
b1 -
b1 (
b11001 *
#104
b0 "
b0 -
b0 (
#105
b11011 $
b11011 /
b11011 2
b1 "
b1 -
b1 (
b11010 *
#108
b0 "
b0 -
b0 (
#109
b11100 $
b11100 /
b11100 2
b1 "
b1 -
b1 (
b11011 *
#112
b0 "
b0 -
b0 (
#113
b11101 $
b11101 /
b11101 2
b1 "
b1 -
b1 (
b11100 *
#116
b0 "
b0 -
b0 (
#117
b11110 $
b11110 /
b11110 2
b1 "
b1 -
b1 (
b11101 *
#120
b0 "
b0 -
b0 (
#121
b11111 $
b11111 /
b11111 2
b1 "
b1 -
b1 (
b11110 *
#124
b0 "
b0 -
b0 (
#125
b100000 $
b100000 /
b100000 2
b1 "
b1 -
b1 (
b11111 *
#128
b0 "
b0 -
b0 (
#129
b100001 $
b100001 /
b100001 2
b1 "
b1 -
b1 (
b100000 *
#132
b0 "
b0 -
b0 (
#133
b100010 $
b100010 /
b100010 2
b1 "
b1 -
b1 (
b100001 *
#136
b0 "
b0 -
b0 (
#137
b100011 $
b100011 /
b100011 2
b1 "
b1 -
b1 (
b100010 *
#140
b0 "
b0 -
b0 (
#141
b100100 $
b100100 /
b100100 2
b1 "
b1 -
b1 (
b100011 *
#144
b0 "
b0 -
b0 (
#145
b100101 $
b100101 /
b100101 2
b1 "
b1 -
b1 (
b100100 *
#148
b0 "
b0 -
b0 (
#149
b100110 $
b100110 /
b100110 2
b1 "
b1 -
b1 (
b100101 *
#152
b0 "
b0 -
b0 (
#153
b100111 $
b100111 /
b100111 2
b1 "
b1 -
b1 (
b100110 *
#156
b0 "
b0 -
b0 (
#157
b101000 $
b101000 /
b101000 2
b1 "
b1 -
b1 (
b100111 *
#160
b0 "
b0 -
b0 (
#161
b101001 $
b101001 /
b101001 2
b1 "
b1 -
b1 (
b101000 *
#164
b0 "
b0 -
b0 (
#165
b101010 $
b101010 /
b101010 2
b1 "
b1 -
b1 (
b101001 *
#168
b0 "
b0 -
b0 (
#169
b101011 $
b101011 /
b101011 2
b1 "
b1 -
b1 (
b101010 *
#172
b0 "
b0 -
b0 (
#173
b101100 $
b101100 /
b101100 2
b1 "
b1 -
b1 (
b101011 *
#176
b0 "
b0 -
b0 (
#177
b101101 $
b101101 /
b101101 2
b1 "
b1 -
b1 (
b101100 *
#180
b0 "
b0 -
b0 (
#181
b101110 $
b101110 /
b101110 2
b1 "
b1 -
b1 (
b101101 *
#184
b0 "
b0 -
b0 (
#185
b101111 $
b101111 /
b101111 2
b1 "
b1 -
b1 (
b101110 *
#188
b0 "
b0 -
b0 (
#189
b110000 $
b110000 /
b110000 2
b1 "
b1 -
b1 (
b101111 *
#192
b0 "
b0 -
b0 (
#193
b110001 $
b110001 /
b110001 2
b1 "
b1 -
b1 (
b110000 *
#196
b0 "
b0 -
b0 (
#197
b110010 $
b110010 /
b110010 2
b1 "
b1 -
b1 (
b110001 *
#200
b0 "
b0 -
b0 (
#201
b110011 $
b110011 /
b110011 2
b1 "
b1 -
b1 (
b110010 *
#204
b0 "
b0 -
b0 (
#205
b110100 $
b110100 /
b110100 2
b1 "
b1 -
b1 (
b110011 *
#208
b0 "
b0 -
b0 (
#209
b110101 $
b110101 /
b110101 2
b1 "
b1 -
b1 (
b110100 *
#212
b0 "
b0 -
b0 (
#213
b110110 $
b110110 /
b110110 2
b1 "
b1 -
b1 (
b110101 *
#216
b0 "
b0 -
b0 (
#217
b110111 $
b110111 /
b110111 2
b1 "
b1 -
b1 (
b110110 *
#220
b0 "
b0 -
b0 (
#221
b111000 $
b111000 /
b111000 2
b1 "
b1 -
b1 (
b110111 *
#224
b0 "
b0 -
b0 (
#225
b111001 $
b111001 /
b111001 2
b1 "
b1 -
b1 (
b111000 *
#228
b0 "
b0 -
b0 (
#229
b111010 $
b111010 /
b111010 2
b1 "
b1 -
b1 (
b111001 *
#232
b0 "
b0 -
b0 (
#233
b111011 $
b111011 /
b111011 2
b1 "
b1 -
b1 (
b111010 *
#236
b0 "
b0 -
b0 (
#237
b111100 $
b111100 /
b111100 2
b1 "
b1 -
b1 (
b111011 *
#240
b0 "
b0 -
b0 (
#241
b111101 $
b111101 /
b111101 2
b1 "
b1 -
b1 (
b111100 *
#244
b0 "
b0 -
b0 (
#245
b111110 $
b111110 /
b111110 2
b1 "
b1 -
b1 (
b111101 *
#248
b0 "
b0 -
b0 (
#249
b111111 $
b111111 /
b111111 2
b1 "
b1 -
b1 (
b111110 *
#252
b0 "
b0 -
b0 (
#253
b1000000 $
b1000000 /
b1000000 2
b1 "
b1 -
b1 (
b111111 *
#256
b0 "
b0 -
b0 (
#257
b1000001 $
b1000001 /
b1000001 2
b1 "
b1 -
b1 (
b1000000 *
#260
b0 "
b0 -
b0 (
#261
b1000010 $
b1000010 /
b1000010 2
b1 "
b1 -
b1 (
b1000001 *
#264
b0 "
b0 -
b0 (
#265
b1000011 $
b1000011 /
b1000011 2
b1 "
b1 -
b1 (
b1000010 *
#268
b0 "
b0 -
b0 (
#269
b1000100 $
b1000100 /
b1000100 2
b1 "
b1 -
b1 (
b1000011 *
#272
b0 "
b0 -
b0 (
#273
b1000101 $
b1000101 /
b1000101 2
b1 "
b1 -
b1 (
b1000100 *
#276
b0 "
b0 -
b0 (
#277
b1000110 $
b1000110 /
b1000110 2
b1 "
b1 -
b1 (
b1000101 *
#280
b0 "
b0 -
b0 (
#281
b1000111 $
b1000111 /
b1000111 2
b1 "
b1 -
b1 (
b1000110 *
#284
b0 "
b0 -
b0 (
#285
b1001000 $
b1001000 /
b1001000 2
b1 "
b1 -
b1 (
b1000111 *
#288
b0 "
b0 -
b0 (
#289
b1001001 $
b1001001 /
b1001001 2
b1 "
b1 -
b1 (
b1001000 *
#292
b0 "
b0 -
b0 (
#293
b1001010 $
b1001010 /
b1001010 2
b1 "
b1 -
b1 (
b1001001 *
#296
b0 "
b0 -
b0 (
#297
b1001011 $
b1001011 /
b1001011 2
b1 "
b1 -
b1 (
b1001010 *
#300
b0 "
b0 -
b0 (
#301
b1001100 $
b1001100 /
b1001100 2
b1 "
b1 -
b1 (
b1001011 *
#304
b0 "
b0 -
b0 (
#305
b1001101 $
b1001101 /
b1001101 2
b1 "
b1 -
b1 (
b1001100 *
#308
b0 "
b0 -
b0 (
#309
b1001110 $
b1001110 /
b1001110 2
b1 "
b1 -
b1 (
b1001101 *
#312
b0 "
b0 -
b0 (
#313
b1001111 $
b1001111 /
b1001111 2
b1 "
b1 -
b1 (
b1001110 *
#316
b0 "
b0 -
b0 (
#317
b1010000 $
b1010000 /
b1010000 2
b1 "
b1 -
b1 (
b1001111 *
#320
b0 "
b0 -
b0 (
#321
b1010001 $
b1010001 /
b1010001 2
b1 "
b1 -
b1 (
b1010000 *
#324
b0 "
b0 -
b0 (
#325
b1010010 $
b1010010 /
b1010010 2
b1 "
b1 -
b1 (
b1010001 *
#328
b0 "
b0 -
b0 (
#329
b1010011 $
b1010011 /
b1010011 2
b1 "
b1 -
b1 (
b1010010 *
#332
b0 "
b0 -
b0 (
#333
b1010100 $
b1010100 /
b1010100 2
b1 "
b1 -
b1 (
b1010011 *
#336
b0 "
b0 -
b0 (
#337
b1010101 $
b1010101 /
b1010101 2
b1 "
b1 -
b1 (
b1010100 *
#340
b0 "
b0 -
b0 (
#341
b1010110 $
b1010110 /
b1010110 2
b1 "
b1 -
b1 (
b1010101 *
#344
b0 "
b0 -
b0 (
#345
b1010111 $
b1010111 /
b1010111 2
b1 "
b1 -
b1 (
b1010110 *
#348
b0 "
b0 -
b0 (
#349
b1011000 $
b1011000 /
b1011000 2
b1 "
b1 -
b1 (
b1010111 *
#352
b0 "
b0 -
b0 (
#353
b1011001 $
b1011001 /
b1011001 2
b1 "
b1 -
b1 (
b1011000 *
#356
b0 "
b0 -
b0 (
#357
b1011010 $
b1011010 /
b1011010 2
b1 "
b1 -
b1 (
b1011001 *
#360
b0 "
b0 -
b0 (
#361
b1011011 $
b1011011 /
b1011011 2
b1 "
b1 -
b1 (
b1011010 *
#364
b0 "
b0 -
b0 (
#365
b1011100 $
b1011100 /
b1011100 2
b1 "
b1 -
b1 (
b1011011 *
#368
b0 "
b0 -
b0 (
#369
b1011101 $
b1011101 /
b1011101 2
b1 "
b1 -
b1 (
b1011100 *
#372
b0 "
b0 -
b0 (
#373
b1011110 $
b1011110 /
b1011110 2
b1 "
b1 -
b1 (
b1011101 *
#376
b0 "
b0 -
b0 (
#377
b1011111 $
b1011111 /
b1011111 2
b1 "
b1 -
b1 (
b1011110 *
#380
b0 "
b0 -
b0 (
#381
b1100000 $
b1100000 /
b1100000 2
b1 "
b1 -
b1 (
b1011111 *
#384
b0 "
b0 -
b0 (
#385
b1100001 $
b1100001 /
b1100001 2
b1 "
b1 -
b1 (
b1100000 *
#388
b0 "
b0 -
b0 (
#389
b1100010 $
b1100010 /
b1100010 2
b1 "
b1 -
b1 (
b1100001 *
#392
b0 "
b0 -
b0 (
#393
b1100011 $
b1100011 /
b1100011 2
b1 "
b1 -
b1 (
b1100010 *
#396
b0 "
b0 -
b0 (
#397
b1 %
b1 0
b1100100 $
b1100100 /
b1100100 2
b1 "
b1 -
b1 (
b1100011 *
#400
b0 "
b0 -
b0 (
#401
b1 "
b1 -
b1 (
b1100100 *
#404
b0 "
b0 -
b0 (
#405
b1 "
b1 -
b1 (
b1100101 *
#408
b0 "
b0 -
b0 (
#409
b1 &
b1 +
b1 1
b1 !
b1 ,
b1 '
b0 *
#410
b0 !
b0 ,
b0 '
#413
b10 &
b10 +
b10 1
b1 !
b1 ,
b1 '
b1 *
#414
b0 !
b0 ,
b0 '
#417
b11 &
b11 +
b11 1
b1 !
b1 ,
b1 '
b10 *
#418
b0 !
b0 ,
b0 '
#421
b100 &
b100 +
b100 1
b1 !
b1 ,
b1 '
b11 *
#422
b0 !
b0 ,
b0 '
#425
b101 &
b101 +
b101 1
b1 !
b1 ,
b1 '
b100 *
#426
b0 !
b0 ,
b0 '
#429
b110 &
b110 +
b110 1
b1 !
b1 ,
b1 '
b101 *
#430
b0 !
b0 ,
b0 '
#433
b111 &
b111 +
b111 1
b1 !
b1 ,
b1 '
b110 *
#434
b0 !
b0 ,
b0 '
#437
b1000 &
b1000 +
b1000 1
b1 !
b1 ,
b1 '
b111 *
#438
b0 !
b0 ,
b0 '
#441
b1001 &
b1001 +
b1001 1
b1 !
b1 ,
b1 '
b1000 *
#442
b0 !
b0 ,
b0 '
#445
b1010 &
b1010 +
b1010 1
b1 !
b1 ,
b1 '
b1001 *
#446
b0 !
b0 ,
b0 '
#449
b1011 &
b1011 +
b1011 1
b1 !
b1 ,
b1 '
b1010 *
#450
b0 !
b0 ,
b0 '
#453
b1100 &
b1100 +
b1100 1
b1 !
b1 ,
b1 '
b1011 *
#454
b0 !
b0 ,
b0 '
#457
b1101 &
b1101 +
b1101 1
b1 !
b1 ,
b1 '
b1100 *
#458
b0 !
b0 ,
b0 '
#461
b1110 &
b1110 +
b1110 1
b1 !
b1 ,
b1 '
b1101 *
#462
b0 !
b0 ,
b0 '
#465
b1111 &
b1111 +
b1111 1
b1 !
b1 ,
b1 '
b1110 *
#466
b0 !
b0 ,
b0 '
#469
b10000 &
b10000 +
b10000 1
b1 !
b1 ,
b1 '
b1111 *
#470
b0 !
b0 ,
b0 '
#473
b10001 &
b10001 +
b10001 1
b1 !
b1 ,
b1 '
b10000 *
#474
b0 !
b0 ,
b0 '
#477
b10010 &
b10010 +
b10010 1
b1 !
b1 ,
b1 '
b10001 *
#478
b0 !
b0 ,
b0 '
#481
b10011 &
b10011 +
b10011 1
b1 !
b1 ,
b1 '
b10010 *
#482
b0 !
b0 ,
b0 '
#485
b10100 &
b10100 +
b10100 1
b1 !
b1 ,
b1 '
b10011 *
#486
b0 !
b0 ,
b0 '
#489
b10101 &
b10101 +
b10101 1
b1 !
b1 ,
b1 '
b10100 *
#490
b0 !
b0 ,
b0 '
#493
b10110 &
b10110 +
b10110 1
b1 !
b1 ,
b1 '
b10101 *
#494
b0 !
b0 ,
b0 '
#497
b10111 &
b10111 +
b10111 1
b1 !
b1 ,
b1 '
b10110 *
#498
b0 !
b0 ,
b0 '
#501
b11000 &
b11000 +
b11000 1
b1 !
b1 ,
b1 '
b10111 *
#502
b0 !
b0 ,
b0 '
#505
b11001 &
b11001 +
b11001 1
b1 !
b1 ,
b1 '
b11000 *
#506
b0 !
b0 ,
b0 '
#509
b11010 &
b11010 +
b11010 1
b1 !
b1 ,
b1 '
b11001 *
#510
b0 !
b0 ,
b0 '
#513
b11011 &
b11011 +
b11011 1
b1 !
b1 ,
b1 '
b11010 *
#514
b0 !
b0 ,
b0 '
#517
b11100 &
b11100 +
b11100 1
b1 !
b1 ,
b1 '
b11011 *
#518
b0 !
b0 ,
b0 '
#521
b11101 &
b11101 +
b11101 1
b1 !
b1 ,
b1 '
b11100 *
#522
b0 !
b0 ,
b0 '
#525
b11110 &
b11110 +
b11110 1
b1 !
b1 ,
b1 '
b11101 *
#526
b0 !
b0 ,
b0 '
#529
b11111 &
b11111 +
b11111 1
b1 !
b1 ,
b1 '
b11110 *
#530
b0 !
b0 ,
b0 '
#533
b100000 &
b100000 +
b100000 1
b1 !
b1 ,
b1 '
b11111 *
#534
b0 !
b0 ,
b0 '
#537
b100001 &
b100001 +
b100001 1
b1 !
b1 ,
b1 '
b100000 *
#538
b0 !
b0 ,
b0 '
#541
b100010 &
b100010 +
b100010 1
b1 !
b1 ,
b1 '
b100001 *
#542
b0 !
b0 ,
b0 '
#545
b100011 &
b100011 +
b100011 1
b1 !
b1 ,
b1 '
b100010 *
#546
b0 !
b0 ,
b0 '
#549
b100100 &
b100100 +
b100100 1
b1 !
b1 ,
b1 '
b100011 *
#550
b0 !
b0 ,
b0 '
#553
b100101 &
b100101 +
b100101 1
b1 !
b1 ,
b1 '
b100100 *
#554
b0 !
b0 ,
b0 '
#557
b100110 &
b100110 +
b100110 1
b1 !
b1 ,
b1 '
b100101 *
#558
b0 !
b0 ,
b0 '
#561
b100111 &
b100111 +
b100111 1
b1 !
b1 ,
b1 '
b100110 *
#562
b0 !
b0 ,
b0 '
#565
b101000 &
b101000 +
b101000 1
b1 !
b1 ,
b1 '
b100111 *
#566
b0 !
b0 ,
b0 '
#569
b101001 &
b101001 +
b101001 1
b1 !
b1 ,
b1 '
b101000 *
#570
b0 !
b0 ,
b0 '
#573
b101010 &
b101010 +
b101010 1
b1 !
b1 ,
b1 '
b101001 *
#574
b0 !
b0 ,
b0 '
#577
b101011 &
b101011 +
b101011 1
b1 !
b1 ,
b1 '
b101010 *
#578
b0 !
b0 ,
b0 '
#581
b101100 &
b101100 +
b101100 1
b1 !
b1 ,
b1 '
b101011 *
#582
b0 !
b0 ,
b0 '
#585
b101101 &
b101101 +
b101101 1
b1 !
b1 ,
b1 '
b101100 *
#586
b0 !
b0 ,
b0 '
#589
b101110 &
b101110 +
b101110 1
b1 !
b1 ,
b1 '
b101101 *
#590
b0 !
b0 ,
b0 '
#593
b101111 &
b101111 +
b101111 1
b1 !
b1 ,
b1 '
b101110 *
#594
b0 !
b0 ,
b0 '
#597
b110000 &
b110000 +
b110000 1
b1 !
b1 ,
b1 '
b101111 *
#598
b0 !
b0 ,
b0 '
#601
b110001 &
b110001 +
b110001 1
b1 !
b1 ,
b1 '
b110000 *
#602
b0 !
b0 ,
b0 '
#605
b110010 &
b110010 +
b110010 1
b1 !
b1 ,
b1 '
b110001 *
#606
b0 !
b0 ,
b0 '
#609
b110011 &
b110011 +
b110011 1
b1 !
b1 ,
b1 '
b110010 *
#610
b0 !
b0 ,
b0 '
#613
b110100 &
b110100 +
b110100 1
b1 !
b1 ,
b1 '
b110011 *
#614
b0 !
b0 ,
b0 '
#617
b110101 &
b110101 +
b110101 1
b1 !
b1 ,
b1 '
b110100 *
#618
b0 !
b0 ,
b0 '
#621
b110110 &
b110110 +
b110110 1
b1 !
b1 ,
b1 '
b110101 *
#622
b0 !
b0 ,
b0 '
#625
b110111 &
b110111 +
b110111 1
b1 !
b1 ,
b1 '
b110110 *
#626
b0 !
b0 ,
b0 '
#629
b111000 &
b111000 +
b111000 1
b1 !
b1 ,
b1 '
b110111 *
#630
b0 !
b0 ,
b0 '
#633
b111001 &
b111001 +
b111001 1
b1 !
b1 ,
b1 '
b111000 *
#634
b0 !
b0 ,
b0 '
#637
b111010 &
b111010 +
b111010 1
b1 !
b1 ,
b1 '
b111001 *
#638
b0 !
b0 ,
b0 '
#641
b111011 &
b111011 +
b111011 1
b1 !
b1 ,
b1 '
b111010 *
#642
b0 !
b0 ,
b0 '
#645
b111100 &
b111100 +
b111100 1
b1 !
b1 ,
b1 '
b111011 *
#646
b0 !
b0 ,
b0 '
#649
b111101 &
b111101 +
b111101 1
b1 !
b1 ,
b1 '
b111100 *
#650
b0 !
b0 ,
b0 '
#653
b111110 &
b111110 +
b111110 1
b1 !
b1 ,
b1 '
b111101 *
#654
b0 !
b0 ,
b0 '
#657
b111111 &
b111111 +
b111111 1
b1 !
b1 ,
b1 '
b111110 *
#658
b0 !
b0 ,
b0 '
#661
b1000000 &
b1000000 +
b1000000 1
b1 !
b1 ,
b1 '
b111111 *
#662
b0 !
b0 ,
b0 '
#665
b1000001 &
b1000001 +
b1000001 1
b1 !
b1 ,
b1 '
b1000000 *
#666
b0 !
b0 ,
b0 '
#669
b1000010 &
b1000010 +
b1000010 1
b1 !
b1 ,
b1 '
b1000001 *
#670
b0 !
b0 ,
b0 '
#673
b1000011 &
b1000011 +
b1000011 1
b1 !
b1 ,
b1 '
b1000010 *
#674
b0 !
b0 ,
b0 '
#677
b1000100 &
b1000100 +
b1000100 1
b1 !
b1 ,
b1 '
b1000011 *
#678
b0 !
b0 ,
b0 '
#681
b1000101 &
b1000101 +
b1000101 1
b1 !
b1 ,
b1 '
b1000100 *
#682
b0 !
b0 ,
b0 '
#685
b1000110 &
b1000110 +
b1000110 1
b1 !
b1 ,
b1 '
b1000101 *
#686
b0 !
b0 ,
b0 '
#689
b1000111 &
b1000111 +
b1000111 1
b1 !
b1 ,
b1 '
b1000110 *
#690
b0 !
b0 ,
b0 '
#693
b1001000 &
b1001000 +
b1001000 1
b1 !
b1 ,
b1 '
b1000111 *
#694
b0 !
b0 ,
b0 '
#697
b1001001 &
b1001001 +
b1001001 1
b1 !
b1 ,
b1 '
b1001000 *
#698
b0 !
b0 ,
b0 '
#701
b1001010 &
b1001010 +
b1001010 1
b1 !
b1 ,
b1 '
b1001001 *
#702
b0 !
b0 ,
b0 '
#705
b1001011 &
b1001011 +
b1001011 1
b1 !
b1 ,
b1 '
b1001010 *
#706
b0 !
b0 ,
b0 '
#709
b1001100 &
b1001100 +
b1001100 1
b1 !
b1 ,
b1 '
b1001011 *
#710
b0 !
b0 ,
b0 '
#713
b1001101 &
b1001101 +
b1001101 1
b1 !
b1 ,
b1 '
b1001100 *
#714
b0 !
b0 ,
b0 '
#717
b1001110 &
b1001110 +
b1001110 1
b1 !
b1 ,
b1 '
b1001101 *
#718
b0 !
b0 ,
b0 '
#721
b1001111 &
b1001111 +
b1001111 1
b1 !
b1 ,
b1 '
b1001110 *
#722
b0 !
b0 ,
b0 '
#725
b1010000 &
b1010000 +
b1010000 1
b1 !
b1 ,
b1 '
b1001111 *
#726
b0 !
b0 ,
b0 '
#729
b1010001 &
b1010001 +
b1010001 1
b1 !
b1 ,
b1 '
b1010000 *
#730
b0 !
b0 ,
b0 '
#733
b1010010 &
b1010010 +
b1010010 1
b1 !
b1 ,
b1 '
b1010001 *
#734
b0 !
b0 ,
b0 '
#737
b1010011 &
b1010011 +
b1010011 1
b1 !
b1 ,
b1 '
b1010010 *
#738
b0 !
b0 ,
b0 '
#741
b1010100 &
b1010100 +
b1010100 1
b1 !
b1 ,
b1 '
b1010011 *
#742
b0 !
b0 ,
b0 '
#745
b1010101 &
b1010101 +
b1010101 1
b1 !
b1 ,
b1 '
b1010100 *
#746
b0 !
b0 ,
b0 '
#749
b1010110 &
b1010110 +
b1010110 1
b1 !
b1 ,
b1 '
b1010101 *
#750
b0 !
b0 ,
b0 '
#753
b1010111 &
b1010111 +
b1010111 1
b1 !
b1 ,
b1 '
b1010110 *
#754
b0 !
b0 ,
b0 '
#757
b1011000 &
b1011000 +
b1011000 1
b1 !
b1 ,
b1 '
b1010111 *
#758
b0 !
b0 ,
b0 '
#761
b1011001 &
b1011001 +
b1011001 1
b1 !
b1 ,
b1 '
b1011000 *
#762
b0 !
b0 ,
b0 '
#765
b1011010 &
b1011010 +
b1011010 1
b1 !
b1 ,
b1 '
b1011001 *
#766
b0 !
b0 ,
b0 '
#769
b1011011 &
b1011011 +
b1011011 1
b1 !
b1 ,
b1 '
b1011010 *
#770
b0 !
b0 ,
b0 '
#773
b1011100 &
b1011100 +
b1011100 1
b1 !
b1 ,
b1 '
b1011011 *
#774
b0 !
b0 ,
b0 '
#777
b1011101 &
b1011101 +
b1011101 1
b1 !
b1 ,
b1 '
b1011100 *
#778
b0 !
b0 ,
b0 '
#781
b1011110 &
b1011110 +
b1011110 1
b1 !
b1 ,
b1 '
b1011101 *
#782
b0 !
b0 ,
b0 '
#785
b1011111 &
b1011111 +
b1011111 1
b1 !
b1 ,
b1 '
b1011110 *
#786
b0 !
b0 ,
b0 '
#789
b1100000 &
b1100000 +
b1100000 1
b1 !
b1 ,
b1 '
b1011111 *
#790
b0 !
b0 ,
b0 '
#793
b1100001 &
b1100001 +
b1100001 1
b1 !
b1 ,
b1 '
b1100000 *
#794
b0 !
b0 ,
b0 '
#797
b1100010 &
b1100010 +
b1100010 1
b1 !
b1 ,
b1 '
b1100001 *
#798
b0 !
b0 ,
b0 '
#801
b1100011 &
b1100011 +
b1100011 1
b1 !
b1 ,
b1 '
b1100010 *
#802
b0 !
b0 ,
b0 '
#805
b1100100 &
b1100100 +
b1100100 1
b1 !
b1 ,
b1 '
b1100011 *
#806
b0 !
b0 ,
b0 '
#809
b1 !
b1 ,
b1 '
b1100100 *
#810
b0 !
b0 ,
b0 '
#813
b1 !
b1 ,
b1 '
b1100101 *
#814
b0 !
b0 ,
b0 '
#817
b0 %
b0 0
b0 $
b0 /
b0 2
b0 &
b0 +
b0 1
b1 #
b1 .
b1 )
b1100110 *
